README.md
main.py
pyproject.toml
mx_rag.egg-info/PKG-INFO
mx_rag.egg-info/SOURCES.txt
mx_rag.egg-info/dependency_links.txt
mx_rag.egg-info/top_level.txt