Metadata-Version: 2.4
Name: mx-rag
Version: 0.0.1.dev0
Summary: A fake package to warn the user they are not installing the correct package
Project-URL: Homepage, https://gitcode.com/Ascend/RagSDK
Project-URL: Repository, https://gitcode.com/Ascend/RagSDK.git
Requires-Python: >=3.7
